{
  "migrationComplete": true,
  "timestamp": "2025-06-22T15:58:30.716Z",
  "finalStats": {
    "totalSongs": 161,
    "tclSongs": 30,
    "ilseSongs": 131,
    "songsWithLyrics": 120,
    "songsWithPlaceholders": 41,
    "extractionRate": "75%"
  },
  "validation": {
    "canonicalCatalogEnforced": true,
    "noDuplicates": true,
    "exactCount": true,
    "artistDistributionCorrect": true
  },
  "nextSteps": [
    "Database ready for deployment",
    "All 161 songs present in final JSON",
    "Placeholder lyrics can be replaced when additional sources become available",
    "Frontend can handle both actual lyrics and placeholder entries"
  ]
}